### PetersonAlgorithm
컴파일된 Producer.class, Consumer.class 을 Bytecode 를 추출(javap -c)하면 다음과 같다.
```
#### Producer 소스 코드 #####
for (int i = 0; i < 10_000; ++i) {
    flag[0] = true;
    turn = 1;
    
    while (flag[1] && turn == 1) ;
    
    count++;
    flag[0] = false;
}

#### Producer 바이트 코드 #####
PS C:\Users\megac\GitRepo\modules\sunset\java\thread\build\classes\java\test\sunset\thread\peterson> javap -c '.\PetersonAlgorithm$Producer.class'
Compiled from "PetersonAlgorithm.java"

class sunset.thread.peterson.PetersonAlgorithm$Producer implements java.lang.Runnable {
  sunset.thread.peterson.PetersonAlgorithm$Producer();
    Code:
       0: aload_0
       1: invokespecial #1                  // Method java/lang/Object."<init>":()V
       4: return

  public void run();
    Code:
       0: iconst_0              // 상수 0 스택 푸시
       1: istore_1              // 로컬변수섹션[1]에 값을 저장
       2: iload_1               // 로컬변수섹션[1] 값을 읽음
       3: sipush        10000   // 10000 을 스택에 푸시
       6: if_icmpge     57      // if #1 <=(ge) #2 이면 57라인으로
      
      // flag[0] = true 
       9: getstatic     #2      // flag[]
      12: iconst_0              // 상수 0 스택 푸시
      13: iconst_1              // 상수 1 스택 푸시
      14: bastore               // flag[0] 1(true) 저장
      
      // turn = 1
      15: iconst_1              // 상수 1 스택 푸시
      16: putstatic     #3      // turn, 1 저장
      
      // while (flag[1] && turn == 1);
      19: getstatic     #2      // flag[]
      22: iconst_1              
      23: baload                
      24: ifeq          37      // !flag[1] 이면 37 라인으로
      27: getstatic     #3      // turn 
      30: iconst_1              
      31: if_icmpne     37      // turn == 1 이면 37 라인으로
      34: goto          19
      
      // count++;
      37: getstatic     #4      // count      
      40: iconst_1
      41: iadd
      42: putstatic     #4      // count
      
      // flag[0] = false
      45: getstatic     #2      // flag[]   
      48: iconst_0
      49: iconst_0
      50: bastore
      
      51: iinc          1, 1
      54: goto          2
      57: return
}
```

```
##### Consumer 소스 코드 #####
for (int i = 0; i < 10_000; ++i) {
    flag[0] = true;
    turn = 1;
    
    while (flag[1] && turn == 1) ;
    
    count--;
    flag[0] = false;
}

##### Consumer 소스 코드 #####
PS C:\Users\megac\GitRepo\modules\sunset\java\thread\build\classes\java\test\sunset\thread\peterson> javap -c '.\PetersonAlgorithm$Consumer.class'
Compiled from "PetersonAlgorithm.java"

class sunset.thread.peterson.PetersonAlgorithm$Consumer implements java.lang.Runnable {
  sunset.thread.peterson.PetersonAlgorithm$Consumer();
    Code:
       0: aload_0
       1: invokespecial #1                  // Method java/lang/Object."<init>":()V
       4: return

  public void run();
    Code:
       0: iconst_0
       1: istore_1
       2: iload_1
       3: sipush        10000
       6: if_icmpge     56
       
       // flag[1] = true
       9: getstatic     #2                  // flag
      12: iconst_1
      13: iconst_1
      14: bastore
      
      // turn = 0
      15: iconst_0
      16: putstatic     #3                  // turn, 0 저장
      
      // while (flag[0] && turn == 0);
      19: getstatic     #2                  // flag[]
      22: iconst_0
      23: baload
      24: ifeq          36
      27: getstatic     #3                  // turn
      30: ifne          36
      33: goto          19
      
      // count--
      36: getstatic     #4                  // count
      39: iconst_1
      40: isub
      41: putstatic     #4                  // count
      
      // flag[1] = false
      44: getstatic     #2                  // flag
      47: iconst_1
      48: iconst_0
      49: bastore
      
      50: iinc          1, 1
      53: goto          2
      56: return
}
```